{
    "sourceFile": "frontend/app/parts/page.tsx",
    "activeCommit": 0,
    "commits": [
        {
            "activePatchIndex": 1,
            "patches": [
                {
                    "date": 1776529547668,
                    "content": "Index: \n===================================================================\n--- \n+++ \n"
                },
                {
                    "date": 1776530809634,
                    "content": "Index: \n===================================================================\n--- \n+++ \n@@ -4,8 +4,14 @@\n import { useCart } from \"@/context/CartContext\";\r\n import { useLang } from \"@/context/LangContext\";\r\n import { site } from \"@/lib/content\";\r\n \r\n+// Category name translations\r\n+const catNames: Record<string, Record<string, string>> = {\r\n+  en: { Brakes:\"Brakes\", Electrical:\"Electrical\", Engine:\"Engine\", Suspension:\"Suspension\", Filters:\"Filters\", Cooling:\"Cooling\" },\r\n+  es: { Brakes:\"Frenos\", Electrical:\"Eléctrico\", Engine:\"Motor\", Suspension:\"Suspensión\", Filters:\"Filtros\", Cooling:\"Refrigeración\" },\r\n+};\r\n+\r\n const txt = {\r\n   en: {\r\n     eyebrow: \"Parts & Components\",\r\n     title: \"Shop repair parts\",\r\n@@ -103,8 +109,9 @@\n           <span className=\"partLowStock\">Only {part.stock} left</span>\r\n         )}\r\n       </div>\r\n       <div className=\"partInfo\">\r\n+        <p className=\"partCategoryTag\">{catNames[lang]?.[part.category] || part.category}</p>\r\n         {part.brand && <p className=\"partBrand\">{part.brand}</p>}\r\n         <h3 className=\"partName\">{part.name}</h3>\r\n         {part.description && <p className=\"partDesc\">{part.description}</p>}\r\n         {part.compatible_vehicles && (\r\n@@ -392,9 +399,9 @@\n               key={cat}\r\n               className={`partsCatPill ${category === cat ? \"partsCatPillActive\" : \"\"}`}\r\n               onClick={() => setCategory(category === cat ? \"\" : cat)}\r\n             >\r\n-              {cat}\r\n+              {catNames[lang]?.[cat] || cat}\r\n             </button>\r\n           ))}\r\n         </div>\r\n \r\n"
                }
            ],
            "date": 1776529547668,
            "name": "Commit-0",
            "content": "\"use client\";\r\n\r\nimport { useEffect, useState, useCallback } from \"react\";\r\nimport { useCart } from \"@/context/CartContext\";\r\nimport { useLang } from \"@/context/LangContext\";\r\nimport { site } from \"@/lib/content\";\r\n\r\nconst txt = {\r\n  en: {\r\n    eyebrow: \"Parts & Components\",\r\n    title: \"Shop repair parts\",\r\n    sub: \"Quality parts for domestic, Asian and European vehicles.\",\r\n    all: \"All categories\",\r\n    search: \"Search parts...\",\r\n    inStock: \"In stock only\",\r\n    addCart: \"Add to cart\",\r\n    added: \"Added!\",\r\n    noResults: \"No parts found.\",\r\n    cart: \"Cart\",\r\n    empty: \"Your cart is empty.\",\r\n    checkout: \"Proceed to checkout\",\r\n    remove: \"Remove\",\r\n    total: \"Total\",\r\n    qty: \"Qty\",\r\n    // Checkout form\r\n    checkoutTitle: \"Checkout\",\r\n    yourName: \"Full name\",\r\n    email: \"Email\",\r\n    phone: \"Phone\",\r\n    address: \"Shipping address\",\r\n    pay: \"Pay now\",\r\n    paying: \"Processing...\",\r\n    orderOk: \"Order confirmed! We'll contact you shortly.\",\r\n    orderErr: \"Payment failed. Please try again.\",\r\n    back: \"← Back to shop\",\r\n  },\r\n  es: {\r\n    eyebrow: \"Repuestos y Componentes\",\r\n    title: \"Compra repuestos\",\r\n    sub: \"Repuestos de calidad para vehículos domésticos, asiáticos y europeos.\",\r\n    all: \"Todas las categorías\",\r\n    search: \"Buscar repuestos...\",\r\n    inStock: \"Solo en stock\",\r\n    addCart: \"Agregar al carrito\",\r\n    added: \"¡Agregado!\",\r\n    noResults: \"No se encontraron repuestos.\",\r\n    cart: \"Carrito\",\r\n    empty: \"Tu carrito está vacío.\",\r\n    checkout: \"Ir al pago\",\r\n    remove: \"Eliminar\",\r\n    total: \"Total\",\r\n    qty: \"Cant\",\r\n    checkoutTitle: \"Pago\",\r\n    yourName: \"Nombre completo\",\r\n    email: \"Correo\",\r\n    phone: \"Teléfono\",\r\n    address: \"Dirección de envío\",\r\n    pay: \"Pagar ahora\",\r\n    paying: \"Procesando...\",\r\n    orderOk: \"¡Pedido confirmado! Te contactaremos pronto.\",\r\n    orderErr: \"Pago fallido. Intenta de nuevo.\",\r\n    back: \"← Volver a la tienda\",\r\n  },\r\n};\r\n\r\ninterface Part {\r\n  id: number;\r\n  name: string;\r\n  description: string;\r\n  category: string;\r\n  brand: string;\r\n  price: number;\r\n  stock: number;\r\n  image_url: string;\r\n  compatible_vehicles: string;\r\n}\r\n\r\n// ── PART CARD ─────────────────────────────────────────────\r\nfunction PartCard({ part, t }: { part: Part; t: typeof txt[\"en\"] }) {\r\n  const { add } = useCart();\r\n  const [flash, setFlash] = useState(false);\r\n\r\n  const handleAdd = () => {\r\n    add({ id: part.id, name: part.name, price: part.price, image_url: part.image_url });\r\n    setFlash(true);\r\n    setTimeout(() => setFlash(false), 1400);\r\n  };\r\n\r\n  return (\r\n    <article className=\"partCard\">\r\n      <div className=\"partImg\">\r\n        {part.image_url\r\n          ? <img src={part.image_url} alt={part.name} />\r\n          : <div className=\"partImgPlaceholder\">\r\n              <svg width=\"40\" height=\"40\" viewBox=\"0 0 24 24\" fill=\"none\">\r\n                <path d=\"M21 16V8a2 2 0 00-1-1.73l-7-4a2 2 0 00-2 0l-7 4A2 2 0 003 8v8a2 2 0 001 1.73l7 4a2 2 0 002 0l7-4A2 2 0 0021 16z\"\r\n                  stroke=\"currentColor\" strokeWidth=\"1.5\" fill=\"none\"/>\r\n              </svg>\r\n            </div>\r\n        }\r\n        {part.stock <= 0 && <span className=\"partOutStock\">Out of stock</span>}\r\n        {part.stock > 0 && part.stock <= 5 && (\r\n          <span className=\"partLowStock\">Only {part.stock} left</span>\r\n        )}\r\n      </div>\r\n      <div className=\"partInfo\">\r\n        {part.brand && <p className=\"partBrand\">{part.brand}</p>}\r\n        <h3 className=\"partName\">{part.name}</h3>\r\n        {part.description && <p className=\"partDesc\">{part.description}</p>}\r\n        {part.compatible_vehicles && (\r\n          <p className=\"partCompat\">Fits: {part.compatible_vehicles}</p>\r\n        )}\r\n        <div className=\"partFooter\">\r\n          <span className=\"partPrice\">${part.price.toFixed(2)}</span>\r\n          <button\r\n            className={`partAddBtn ${flash ? \"partAdded\" : \"\"}`}\r\n            onClick={handleAdd}\r\n            disabled={part.stock <= 0}\r\n          >\r\n            {flash ? t.added : t.addCart}\r\n          </button>\r\n        </div>\r\n      </div>\r\n    </article>\r\n  );\r\n}\r\n\r\n// ── CART DRAWER ────────────────────────────────────────────\r\nfunction CartDrawer({ open, onClose, onCheckout, t }: {\r\n  open: boolean; onClose: () => void;\r\n  onCheckout: () => void; t: typeof txt[\"en\"];\r\n}) {\r\n  const { items, total, remove, update } = useCart();\r\n\r\n  return (\r\n    <>\r\n      {open && <div className=\"cartBackdrop\" onClick={onClose} />}\r\n      <div className={`cartDrawer ${open ? \"cartOpen\" : \"\"}`}>\r\n        <div className=\"cartHead\">\r\n          <h2>{t.cart}</h2>\r\n          <button onClick={onClose} className=\"cartClose\">✕</button>\r\n        </div>\r\n        {items.length === 0\r\n          ? <p className=\"cartEmpty\">{t.empty}</p>\r\n          : (\r\n            <>\r\n              <div className=\"cartItems\">\r\n                {items.map(item => (\r\n                  <div key={item.id} className=\"cartItem\">\r\n                    {item.image_url && <img src={item.image_url} alt={item.name} className=\"cartItemImg\" />}\r\n                    <div className=\"cartItemInfo\">\r\n                      <p className=\"cartItemName\">{item.name}</p>\r\n                      <p className=\"cartItemPrice\">${(item.price * item.quantity).toFixed(2)}</p>\r\n                    </div>\r\n                    <div className=\"cartItemQty\">\r\n                      <button onClick={() => update(item.id, item.quantity - 1)}>−</button>\r\n                      <span>{item.quantity}</span>\r\n                      <button onClick={() => update(item.id, item.quantity + 1)}>+</button>\r\n                    </div>\r\n                    <button className=\"cartItemRemove\" onClick={() => remove(item.id)}>✕</button>\r\n                  </div>\r\n                ))}\r\n              </div>\r\n              <div className=\"cartFooter\">\r\n                <div className=\"cartTotal\">\r\n                  <span>{t.total}</span>\r\n                  <strong>${total.toFixed(2)}</strong>\r\n                </div>\r\n                <button className=\"cartCheckoutBtn\" onClick={onCheckout}>\r\n                  {t.checkout}\r\n                </button>\r\n              </div>\r\n            </>\r\n          )\r\n        }\r\n      </div>\r\n    </>\r\n  );\r\n}\r\n\r\n// ── CHECKOUT ──────────────────────────────────────────────\r\nfunction CheckoutPage({ onBack, t }: { onBack: () => void; t: typeof txt[\"en\"] }) {\r\n  const { items, total, clear } = useCart();\r\n  const [form, setForm] = useState({ name: \"\", email: \"\", phone: \"\", address: \"\" });\r\n  const [status, setStatus] = useState<\"idle\"|\"paying\"|\"ok\"|\"err\">(\"idle\");\r\n\r\n  const handleSubmit = async (e: React.FormEvent) => {\r\n    e.preventDefault();\r\n    setStatus(\"paying\");\r\n    try {\r\n      // 1. Create order\r\n      const orderRes = await fetch(`${site.apiBase}/orders/`, {\r\n        method: \"POST\",\r\n        headers: { \"Content-Type\": \"application/json\" },\r\n        body: JSON.stringify({\r\n          customer_name: form.name,\r\n          customer_email: form.email,\r\n          customer_phone: form.phone,\r\n          shipping_address: form.address,\r\n          items: items.map(i => ({ part_id: i.id, quantity: i.quantity })),\r\n        }),\r\n      });\r\n      if (!orderRes.ok) throw new Error();\r\n      const order = await orderRes.json();\r\n\r\n      // 2. Create payment intent\r\n      const piRes = await fetch(`${site.apiBase}/orders/payment-intent`, {\r\n        method: \"POST\",\r\n        headers: { \"Content-Type\": \"application/json\" },\r\n        body: JSON.stringify({ order_id: order.id }),\r\n      });\r\n\r\n      if (!piRes.ok) {\r\n        // No Stripe configured — mark as confirmed anyway (COD / manual)\r\n        clear();\r\n        setStatus(\"ok\");\r\n        return;\r\n      }\r\n\r\n      // 3. If Stripe is configured, load Stripe.js and confirm\r\n      const { client_secret } = await piRes.json();\r\n      // @ts-ignore\r\n      const stripe = window.Stripe?.(process.env.NEXT_PUBLIC_STRIPE_KEY || \"\");\r\n      if (stripe && client_secret) {\r\n        const { error } = await stripe.confirmPayment({\r\n          clientSecret: client_secret,\r\n          confirmParams: { return_url: window.location.href },\r\n          redirect: \"if_required\",\r\n        });\r\n        if (error) throw error;\r\n      }\r\n\r\n      clear();\r\n      setStatus(\"ok\");\r\n    } catch {\r\n      setStatus(\"err\");\r\n    }\r\n  };\r\n\r\n  if (status === \"ok\") {\r\n    return (\r\n      <div className=\"checkoutSuccess\">\r\n        <svg width=\"56\" height=\"56\" viewBox=\"0 0 24 24\" fill=\"none\">\r\n          <circle cx=\"12\" cy=\"12\" r=\"10\" stroke=\"#22c55e\" strokeWidth=\"1.8\"/>\r\n          <path d=\"M8 12l3 3 5-5\" stroke=\"#22c55e\" strokeWidth=\"1.8\" strokeLinecap=\"round\"/>\r\n        </svg>\r\n        <p>{t.orderOk}</p>\r\n        <button className=\"partAddBtn\" onClick={onBack}>{t.back}</button>\r\n      </div>\r\n    );\r\n  }\r\n\r\n  return (\r\n    <div className=\"checkoutWrap\">\r\n      <button className=\"checkoutBack\" onClick={onBack}>{t.back}</button>\r\n      <div className=\"checkoutGrid\">\r\n        {/* Left — summary */}\r\n        <div className=\"checkoutSummary\">\r\n          <h2>{t.cart}</h2>\r\n          {items.map(i => (\r\n            <div key={i.id} className=\"checkoutItem\">\r\n              <span>{i.name} × {i.quantity}</span>\r\n              <span>${(i.price * i.quantity).toFixed(2)}</span>\r\n            </div>\r\n          ))}\r\n          <div className=\"checkoutItemTotal\">\r\n            <strong>{t.total}</strong>\r\n            <strong>${total.toFixed(2)}</strong>\r\n          </div>\r\n        </div>\r\n\r\n        {/* Right — form */}\r\n        <form className=\"checkoutForm\" onSubmit={handleSubmit}>\r\n          <h2>{t.checkoutTitle}</h2>\r\n          <input className=\"ctInput\" placeholder={t.yourName} required\r\n            value={form.name} onChange={e => setForm({...form, name: e.target.value})} />\r\n          <input className=\"ctInput\" placeholder={t.email} type=\"email\" required\r\n            value={form.email} onChange={e => setForm({...form, email: e.target.value})} />\r\n          <input className=\"ctInput\" placeholder={t.phone} type=\"tel\" required\r\n            value={form.phone} onChange={e => setForm({...form, phone: e.target.value})} />\r\n          <textarea className=\"ctInput ctTextarea\" placeholder={t.address} required rows={3}\r\n            value={form.address} onChange={e => setForm({...form, address: e.target.value})} />\r\n          <button type=\"submit\" className=\"cartCheckoutBtn\"\r\n            disabled={status === \"paying\"}>\r\n            {status === \"paying\" ? t.paying : `${t.pay} — $${total.toFixed(2)}`}\r\n          </button>\r\n          {status === \"err\" && <p className=\"ctStatusErr\">{t.orderErr}</p>}\r\n        </form>\r\n      </div>\r\n    </div>\r\n  );\r\n}\r\n\r\n// ── MAIN PAGE ─────────────────────────────────────────────\r\nexport default function PartsPage() {\r\n  const { lang } = useLang();\r\n  const t = txt[lang];\r\n  const { count } = useCart();\r\n\r\n  const [parts, setParts]         = useState<Part[]>([]);\r\n  const [categories, setCategories] = useState<string[]>([]);\r\n  const [loading, setLoading]     = useState(true);\r\n  const [cartOpen, setCartOpen]   = useState(false);\r\n  const [checkout, setCheckout]   = useState(false);\r\n\r\n  // Filters\r\n  const [category, setCategory]   = useState(\"\");\r\n  const [search, setSearch]       = useState(\"\");\r\n  const [inStock, setInStock]     = useState(false);\r\n\r\n  const fetchParts = useCallback(async () => {\r\n    setLoading(true);\r\n    const params = new URLSearchParams();\r\n    if (category) params.set(\"category\", category);\r\n    if (search)   params.set(\"search\", search);\r\n    if (inStock)  params.set(\"in_stock\", \"true\");\r\n    try {\r\n      const res = await fetch(`${site.apiBase}/parts/?${params}`);\r\n      const data = await res.json();\r\n      setParts(data);\r\n    } catch {\r\n      setParts([]);\r\n    }\r\n    setLoading(false);\r\n  }, [category, search, inStock]);\r\n\r\n  useEffect(() => { fetchParts(); }, [fetchParts]);\r\n\r\n  useEffect(() => {\r\n    fetch(`${site.apiBase}/parts/meta/categories`)\r\n      .then(r => r.json())\r\n      .then(setCategories)\r\n      .catch(() => {});\r\n  }, []);\r\n\r\n  if (checkout) {\r\n    return (\r\n      <main className=\"innerPage\">\r\n        <div className=\"container\">\r\n          <CheckoutPage onBack={() => setCheckout(false)} t={t} />\r\n        </div>\r\n      </main>\r\n    );\r\n  }\r\n\r\n  return (\r\n    <main className=\"innerPage\">\r\n      <div className=\"container\">\r\n\r\n        {/* Header */}\r\n        <div className=\"partsHeader\">\r\n          <div>\r\n            <p className=\"eyebrow\">{t.eyebrow}</p>\r\n            <h1 className=\"partsTitle\">{t.title}</h1>\r\n            <p className=\"partsSub\">{t.sub}</p>\r\n          </div>\r\n          <button className=\"cartBtn\" onClick={() => setCartOpen(true)}>\r\n            <svg width=\"20\" height=\"20\" viewBox=\"0 0 24 24\" fill=\"none\">\r\n              <path d=\"M6 2L3 6v14a2 2 0 002 2h14a2 2 0 002-2V6l-3-4z\" stroke=\"currentColor\" strokeWidth=\"1.6\"/>\r\n              <line x1=\"3\" y1=\"6\" x2=\"21\" y2=\"6\" stroke=\"currentColor\" strokeWidth=\"1.6\"/>\r\n              <path d=\"M16 10a4 4 0 01-8 0\" stroke=\"currentColor\" strokeWidth=\"1.6\"/>\r\n            </svg>\r\n            {t.cart}\r\n            {count > 0 && <span className=\"cartBadge\">{count}</span>}\r\n          </button>\r\n        </div>\r\n\r\n        {/* Search + stock filter */}\r\n        <div className=\"partsFilters\">\r\n          <input\r\n            className=\"partsSearch ctInput\"\r\n            placeholder={t.search}\r\n            value={search}\r\n            onChange={e => setSearch(e.target.value)}\r\n          />\r\n          <label className=\"partsInStock\">\r\n            <input type=\"checkbox\" checked={inStock} onChange={e => setInStock(e.target.checked)} />\r\n            {t.inStock}\r\n          </label>\r\n        </div>\r\n\r\n        {/* Category pills */}\r\n        <div className=\"partsCatPills\">\r\n          <button\r\n            className={`partsCatPill ${category === \"\" ? \"partsCatPillActive\" : \"\"}`}\r\n            onClick={() => setCategory(\"\")}\r\n          >\r\n            {t.all}\r\n          </button>\r\n          {categories.map(cat => (\r\n            <button\r\n              key={cat}\r\n              className={`partsCatPill ${category === cat ? \"partsCatPillActive\" : \"\"}`}\r\n              onClick={() => setCategory(category === cat ? \"\" : cat)}\r\n            >\r\n              {cat}\r\n            </button>\r\n          ))}\r\n        </div>\r\n\r\n        {/* Results count */}\r\n        {!loading && (\r\n          <p className=\"partsCount\">{parts.length} {parts.length === 1 ? \"part\" : \"parts\"} found</p>\r\n        )}\r\n\r\n        {/* Grid */}\r\n        {loading\r\n          ? <div className=\"partsLoading\">\r\n              {[...Array(6)].map((_,i) => <div key={i} className=\"partSkeleton\" />)}\r\n            </div>\r\n          : parts.length === 0\r\n            ? <p className=\"partsEmpty\">{t.noResults}</p>\r\n            : <div className=\"partsGrid\">\r\n                {parts.map(p => <PartCard key={p.id} part={p} t={t} />)}\r\n              </div>\r\n        }\r\n      </div>\r\n\r\n      {/* Cart drawer */}\r\n      <CartDrawer\r\n        open={cartOpen}\r\n        onClose={() => setCartOpen(false)}\r\n        onCheckout={() => { setCartOpen(false); setCheckout(true); }}\r\n        t={t}\r\n      />\r\n    </main>\r\n  );\r\n}"
        }
    ]
}